odoo10_addon_base_custom_attribute-10.0.0.0.2-nspkg.pth
odoo/addons/base_custom_attribute/README.rst
odoo/addons/base_custom_attribute/__init__.py
odoo/addons/base_custom_attribute/__manifest__.py
odoo/addons/base_custom_attribute/demo/attribute.xml
odoo/addons/base_custom_attribute/i18n/base_custom_attributes.pot
odoo/addons/base_custom_attribute/i18n/es.po
odoo/addons/base_custom_attribute/i18n/fr.po
odoo/addons/base_custom_attribute/i18n/it.po
odoo/addons/base_custom_attribute/i18n/zh_CN.po
odoo/addons/base_custom_attribute/models/__init__.py
odoo/addons/base_custom_attribute/models/attribute_attribute.py
odoo/addons/base_custom_attribute/models/attribute_group.py
odoo/addons/base_custom_attribute/models/attribute_location.py
odoo/addons/base_custom_attribute/models/attribute_option.py
odoo/addons/base_custom_attribute/models/attribute_set.py
odoo/addons/base_custom_attribute/models/ir_model_fields.py
odoo/addons/base_custom_attribute/security/attribute_security.xml
odoo/addons/base_custom_attribute/security/ir.model.access.csv
odoo/addons/base_custom_attribute/tests/__init__.py
odoo/addons/base_custom_attribute/tests/test_custom_attribute.py
odoo/addons/base_custom_attribute/views/attribute_attribute_view.xml
odoo/addons/base_custom_attribute/views/attribute_group_view.xml
odoo/addons/base_custom_attribute/views/attribute_option_view.xml
odoo/addons/base_custom_attribute/views/attribute_set_view.xml
odoo/addons/base_custom_attribute/views/menu_view.xml
odoo/addons/base_custom_attribute/wizard/__init__.py
odoo/addons/base_custom_attribute/wizard/attribute_option_wizard.py
odoo/addons/base_custom_attribute/wizard/attribute_option_wizard_view.xml
odoo10_addon_base_custom_attribute-10.0.0.0.2.dist-info/METADATA
odoo10_addon_base_custom_attribute-10.0.0.0.2.dist-info/WHEEL
odoo10_addon_base_custom_attribute-10.0.0.0.2.dist-info/namespace_packages.txt
odoo10_addon_base_custom_attribute-10.0.0.0.2.dist-info/top_level.txt
odoo10_addon_base_custom_attribute-10.0.0.0.2.dist-info/RECORD
